dash_docset_builder/__init__.py
dash_docset_builder/argparse_template.py
dash_docset_builder/db.py
dash_docset_builder/docset_skeleton.py
dash_docset_builder/get_title.py
dash_docset_builder/gnu.py
dash_docset_builder/py.typed
dash_docset_builder/set_stylesheet.py
dash_docset_builder-2026.1.25.dist-info/licenses/LICENSE
dash_docset_builder-2026.1.25.dist-info/METADATA
dash_docset_builder-2026.1.25.dist-info/WHEEL
dash_docset_builder-2026.1.25.dist-info/top_level.txt
dash_docset_builder-2026.1.25.dist-info/RECORD
