Metadata-Version: 2.4
Name: dash_docset_builder
Version: 2026.1.25
Summary: Library for generating dash docsets
Author-email: Louie Shprung <lshprung@tutanota.com>
License-Expression: GPL-3.0-or-later
Project-URL: Homepage, https://github.com/lshprung/dash-docset-builder
Project-URL: Issues, https://github.com/lshprung/dash-docset-builder/issues
Classifier: Operating System :: OS Independent
Classifier: Programming Language :: Python :: 3
Requires-Python: >=3.10
License-File: LICENSE
Requires-Dist: beautifulsoup4
Requires-Dist: requests
Dynamic: license-file
